rest_framework_csv/__init__.py
rest_framework_csv/misc.py
rest_framework_csv/models.py
rest_framework_csv/orderedrows.py
rest_framework_csv/parsers.py
rest_framework_csv/renderers.py
rest_framework_csv/tests.py
rest_framework_csv/__pycache__/__init__.cpython-311.pyc
rest_framework_csv/__pycache__/__init__.cpython-37.pyc
rest_framework_csv/__pycache__/__init__.cpython-39.pyc
rest_framework_csv/__pycache__/misc.cpython-311.pyc
rest_framework_csv/__pycache__/misc.cpython-37.pyc
rest_framework_csv/__pycache__/misc.cpython-39.pyc
rest_framework_csv/__pycache__/models.cpython-311.pyc
rest_framework_csv/__pycache__/models.cpython-37.pyc
rest_framework_csv/__pycache__/models.cpython-39.pyc
rest_framework_csv/__pycache__/orderedrows.cpython-311.pyc
rest_framework_csv/__pycache__/orderedrows.cpython-37.pyc
rest_framework_csv/__pycache__/orderedrows.cpython-39.pyc
rest_framework_csv/__pycache__/parsers.cpython-311.pyc
rest_framework_csv/__pycache__/parsers.cpython-37.pyc
rest_framework_csv/__pycache__/parsers.cpython-39.pyc
rest_framework_csv/__pycache__/renderers.cpython-311.pyc
rest_framework_csv/__pycache__/renderers.cpython-37.pyc
rest_framework_csv/__pycache__/renderers.cpython-39.pyc
rest_framework_csv/__pycache__/tests.cpython-311.pyc
rest_framework_csv/__pycache__/tests.cpython-37.pyc
rest_framework_csv/__pycache__/tests.cpython-39.pyc
rest_framework_csv/testfixtures/nonewlines.csv
djangorestframework_csv-3.0.1.dist-info/LICENSE
djangorestframework_csv-3.0.1.dist-info/METADATA
djangorestframework_csv-3.0.1.dist-info/WHEEL
djangorestframework_csv-3.0.1.dist-info/top_level.txt
djangorestframework_csv-3.0.1.dist-info/RECORD
